django_vendor_images-0.1.0.dist-info/licenses/LICENSE
vendor_images/__init__.py
vendor_images/models.py
vendor_images/utils.py
vendor_images/tests/__init__.py
vendor_images/tests/test_models.py
django_vendor_images-0.1.0.dist-info/METADATA
django_vendor_images-0.1.0.dist-info/WHEEL
django_vendor_images-0.1.0.dist-info/top_level.txt
django_vendor_images-0.1.0.dist-info/RECORD
