Metadata-Version: 2.4
Name: django-vendor-images
Version: 0.1.0
Summary: Django reusable image model for vendor/shop images
Home-page: https://github.com/mehran-jafari/django-vendor-images
Author: Mehran Jafari
Author-email: Mehran Jafari <eng.mehranjafarii@gmail.com>
Requires-Python: >=3.8
License-File: LICENSE
Requires-Dist: django>=3.2
Requires-Dist: Pillow>=9.0
Dynamic: author
Dynamic: home-page
Dynamic: license-file
